setup.py
distributionsjx/Binomialdistribution.py
distributionsjx/Gaussiandistribution.py
distributionsjx/Generaldistribution.py
distributionsjx/__init__.py
distributionsjx.egg-info/PKG-INFO
distributionsjx.egg-info/SOURCES.txt
distributionsjx.egg-info/dependency_links.txt
distributionsjx.egg-info/not-zip-safe
distributionsjx.egg-info/top_level.txt